data_scraper/__init__.py
data_scraper/content_extractor.py
data_scraper/docx_to_pdf_converter.py
data_scraper/url_extractor.py
tests/__init__.py
tests/test.py
tests/test_content_extractor.py
tests/test_docx_to_pdf_converter.py
tests/test_url_extractor.py
DataScraper-0.1.1.dist-info/LICENSE
DataScraper-0.1.1.dist-info/METADATA
DataScraper-0.1.1.dist-info/WHEEL
DataScraper-0.1.1.dist-info/entry_points.txt
DataScraper-0.1.1.dist-info/top_level.txt
DataScraper-0.1.1.dist-info/RECORD
