Metadata-Version: 2.1
Name: DataScraper
Version: 0.1.1
Summary: A web scraper to extract URLs, content from websites and convert DOCX to PDF.
Home-page: https://github.com/mukhtarulislam/Datascrapper.git
Author: Mukhtar ul Islam
Author-email: mukhtarulislam88@hotmail.com
Classifier: Programming Language :: Python :: 3
Classifier: License :: OSI Approved :: MIT License
Classifier: Operating System :: OS Independent
Requires-Python: >=3.6
License-File: LICENSE
Requires-Dist: requests
Requires-Dist: beautifulsoup4
Requires-Dist: python-docx
Requires-Dist: reportlab
Requires-Dist: pywin32; platform_system == "Windows"
